meraki_env/__init__.py
meraki_env/meraki_env.py
meraki_env-0.1.4.dist-info/WHEEL
meraki_env-0.1.4.dist-info/METADATA
meraki_env-0.1.4.dist-info/RECORD
